enumerate_skip/version.py
enumerate_skip/funcs.py
enumerate_skip/__init__.py
enumerate_skip-1.0.dist-info/top_level.txt
enumerate_skip-1.0.dist-info/METADATA
enumerate_skip-1.0.dist-info/DESCRIPTION.rst
enumerate_skip-1.0.dist-info/RECORD
enumerate_skip-1.0.dist-info/WHEEL
enumerate_skip-1.0.dist-info/metadata.json
