Metadata-Version: 1.1
Name: enumerate-skip
Version: 1.0
Summary: enumerate extended to support manual advancement or skipping      of the index
Home-page: ['http://github.com/mineo/enumerate_skip']
Author: Wieland Hoffmann
Author-email: themineo@gmail.com
License: MIT
Download-URL: ['https://github.com/mineo/enumerate_skip/tarball/master']
Platform: UNKNOWN
Classifier: Development Status :: 5 - Production/Stable
Classifier: License :: OSI Approved :: MIT License
Classifier: Natural Language :: English
Classifier: Operating System :: OS Independent
Classifier: Programming Language :: Python :: 2.6
Classifier: Programming Language :: Python :: 2.7
Classifier: Programming Language :: Python :: 3.2
Classifier: Programming Language :: Python :: 3.3
Classifier: Programming Language :: Python :: 3.4
